coinnest/__init__.py
coinnest/client.py
coinnest_python_client-0.0.1.dist-info/DESCRIPTION.rst
coinnest_python_client-0.0.1.dist-info/METADATA
coinnest_python_client-0.0.1.dist-info/RECORD
coinnest_python_client-0.0.1.dist-info/WHEEL
coinnest_python_client-0.0.1.dist-info/metadata.json
coinnest_python_client-0.0.1.dist-info/top_level.txt
tests/__init__.py
tests/test_get_ticker.py
