Metadata-Version: 2.0
Name: coinnest-python-client
Version: 0.0.1
Summary: Client for Coinnest API
Home-page: https://github.com/Leop0ld/coinnest-python-client.git
Author: Leop0ld
Author-email: iam@leop0ld.org
License: MIT
Platform: UNKNOWN
Classifier: Programming Language :: Python :: 3.4
Classifier: Programming Language :: Python :: 3.5
Classifier: Programming Language :: Python :: 3.6
Requires-Python: >=3.4
Requires-Dist: requests
